dictutils/__init__.py
dictutils/mergedict.py
dictutils/nestagg.py
dictutils/ops.py
dictutils/pivot.py
dictutils/py.typed
dictutils/qsdict.py
dictutils-1.0.1.dist-info/licenses/LICENSE
dictutils-1.0.1.dist-info/METADATA
dictutils-1.0.1.dist-info/WHEEL
dictutils-1.0.1.dist-info/top_level.txt
dictutils-1.0.1.dist-info/RECORD
