Metadata-Version: 2.4
Name: dictutils
Version: 1.0.1
Summary: Small utilities for nested dicts: merge, pivot, grouping/aggregation.
Author-email: Adi Eyal <adi@openup.org.za>
License: MIT
Project-URL: Homepage, https://github.com/adieyal/dictutils
Project-URL: Repository, https://github.com/adieyal/dictutils
Project-URL: Documentation, https://dictutils.readthedocs.io/en/latest/
Project-URL: Issues, https://github.com/adieyal/dictutils/issues
Project-URL: Changelog, https://github.com/adieyal/dictutils/blob/master/CHANGELOG.md
Classifier: Development Status :: 5 - Production/Stable
Classifier: Intended Audience :: Developers
Classifier: License :: OSI Approved :: MIT License
Classifier: Programming Language :: Python :: 3
Classifier: Programming Language :: Python :: 3.9
Classifier: Programming Language :: Python :: 3.10
Classifier: Programming Language :: Python :: 3.11
Classifier: Programming Language :: Python :: 3.12
Classifier: Programming Language :: Python :: 3.13
Classifier: Topic :: Software Development :: Libraries :: Python Modules
Requires-Python: >=3.9
License-File: LICENSE
Provides-Extra: test
Requires-Dist: pytest>=8.0.0; extra == "test"
Provides-Extra: typecheck
Requires-Dist: mypy>=1.11.0; extra == "typecheck"
Provides-Extra: lint
Requires-Dist: ruff>=0.4.0; extra == "lint"
Requires-Dist: black>=24.0.0; extra == "lint"
Requires-Dist: pre-commit>=3.0.0; extra == "lint"
Requires-Dist: pyupgrade>=3.15.0; extra == "lint"
Provides-Extra: docs
Requires-Dist: sphinx>=7.3; extra == "docs"
Requires-Dist: myst-parser>=2.0; extra == "docs"
Requires-Dist: alabaster>=0.7.14; extra == "docs"
Requires-Dist: sphinx-copybutton>=0.5.2; extra == "docs"
Requires-Dist: sphinx-autodoc-typehints>=2.2.1; extra == "docs"
Requires-Dist: sphinx-autobuild>=2024.4.16; extra == "docs"
Dynamic: license-file
